pymummer/__init__.py
pymummer/_version.py
pymummer/alignment.py
pymummer/coords_file.py
pymummer/nucmer.py
pymummer/snp.py
pymummer/snp_file.py
pymummer/syscall.py
pymummer/variant.py
pymummer-0.12.0.dist-info/METADATA
pymummer-0.12.0.dist-info/WHEEL
pymummer-0.12.0.dist-info/licenses/AUTHORS
pymummer-0.12.0.dist-info/licenses/LICENSE
pymummer-0.12.0.dist-info/RECORD
