Metadata-Version: 2.4
Name: pymummer
Version: 0.12.0
Summary: Wrapper for MUMmer
Project-URL: homepage, https://github.com/sanger-pathogens/pymummer
Project-URL: documentation, https://github.com/sanger-pathogens/pymummer
Project-URL: repository, https://github.com/sanger-pathogens/pymummer
Author-email: Martin Hunt <path-help@sanger.ac.uk>, Nishadi De Silva <path-help@sanger.ac.uk>
License: GPLv3
License-File: AUTHORS
License-File: LICENSE
Classifier: Development Status :: 4 - Beta
Classifier: License :: OSI Approved :: GNU General Public License v3 (GPLv3)
Classifier: Programming Language :: Python :: 3 :: Only
Classifier: Topic :: Scientific/Engineering :: Bio-Informatics
Requires-Python: >=3.8
Requires-Dist: pyfastaq>=3.10.0
Provides-Extra: tests
Requires-Dist: pytest; extra == 'tests'
